cla/cla_Nbit.v
module CLA_4bit(a, b, cin, sum, cout);
    input [3:0] a;
    input [3:0] b;
    input cin;
    output [3:0] sum;
    output cout;

    wire G;
    wire P;

    CLA_4bit_P_G clapg0(.a(a), .b(b), .cin(cin), .sum(sum), .P(P), .G(G));

    assign cout = G | (P & cin);

endmodule


module CLA_4bit_P_G(a, b, cin, sum, P, G);
    input [3:0] a;
    input [3:0] b;
    input cin;
    output [3:0] sum;
    output P;
    output G;

    wire [3:0] p;
    wire [3:0] g;
    wire [3:0] c;

    assign g = a & b;
    assign p = a ^ b;

    assign c[0] = cin;
    assign c[1] = g[0] | p[0] & c[0];
    assign c[2] = g[1] | p[1] & c[1];
    assign c[3] = g[2] | p[2] & c[2];

    assign sum = p ^ c;

    assign P = p[0] & p[1] & p[2] & p[3];
    assign G = g[3] | (p[3] & g[2]) | (p[3] & p[2] & g[1]) | (p[3] & p[2] & p[1] & g[0]);

endmodule


module lookahead_carry_unit_16_bit(P0, G0, P1, G1, P2, G2, P3, G3, cin, C4, C8, C12, C16, GF, PF);
    input P0, P1, P2, P3, G0, G1, G2, G3, cin;
    output C4, C8, C12, C16;
    output PF;
    output GF;

    assign C4 = G0 | (P0 & cin);
    assign C8 = G1 | (P1 & C4);
    assign C12 = G2 | (P2 & C8);
    assign C16 = G3 | (P3 & C12);

    assign GF = G3 | (P3 & G2) | (P3 & P2 & G1) | (P3 & P2 & P1 & G0);
    assign PF = P3 & P2 & P1 & P0;

endmodule


module CLA_16bit(a, b, cin, sum, cout, Pout, Gout);
    input [15:0] a;
    input [15:0] b;
    input cin;
    output [15:0] sum;
    output cout, Pout, Gout;
    wire [3:0] cout_intermed;
    wire [3:0] P;
    wire [3:0] G;
    wire C4, C8, C12, C16;

    CLA_4bit_P_G cla0(.a(a[3:0]), .b(b[3:0]), .cin(cin), .sum(sum[3:0]), .P(P[0]), .G(G[0]));
    CLA_4bit_P_G cla1(.a(a[7:4]), .b(b[7:4]), .cin(C4), .sum(sum[7:4]), .P(P[1]), .G(G[1]));
    CLA_4bit_P_G cla2(.a(a[11:8]), .b(b[11:8]), .cin(C8), .sum(sum[11:8]), .P(P[2]), .G(G[2]));
    CLA_4bit_P_G cla3(.a(a[15:12]), .b(b[15:12]), .cin(C12), .sum(sum[15:12]), .P(P[3]), .G(G[3]));

    lookahead_carry_unit_16_bit lcu0(.P0(P[0]), .G0(G[0]), .P1(P[1]), .G1(G[1]), .P2(P[2]), .G2(G[2]), .P3(P[3]), .G3(G[3]), .cin(cin), .C4(C4), .C8(C8), .C12(C12), .C16(C16), .GF(Gout), .PF(Pout));

    assign cout = C16;


endmodule


module lookahead_carry_unit_32_bit (P0, G0, P1, G1, cin, C16, C32, GF, PF);
    input P0, P1, G0, G1, cin;
    output C16, C32;
    output PF, GF;

    assign C16 = G0 | (P0 & cin);
    assign C32 = G1 | (P1 & C16);

    assign PF = P0 & P1;
    assign GF = G1 | (P1 & G0);

endmodule


module CLA_32bit(a, b, cin, sum, cout, Pout, Gout);

    input [31:0] a;
    input [31:0] b;
    input cin;
    output [31:0] sum;
    output cout;
    output Pout, Gout;

    wire P0, G0, P1, G1;
    wire C16, C32;

    CLA_16bit cla5(.a(a[15:0]), .b(b[15:0]), .cin(cin), .sum(sum[15:0]), .cout(), .Pout(P0), .Gout(G0));
    CLA_16bit cla6(.a(a[31:16]), .b(b[31:16]), .cin(C16), .sum(sum[31:16]), .cout(), .Pout(P1), .Gout(G1));

    lookahead_carry_unit_32_bit lcu1(.P0(P0), .G0(G0), .P1(P1), .G1(G1), .cin(cin), .C16(C16), .C32(C32), .GF(Gout), .PF(Pout));

    assign cout = C32;

endmodule

cla/tb_cla_32bit.v
`timescale 1ns/1ps
`include "cla_Nbit.v"

module tb_cla_32bit;

parameter N = 32;     /*Change this to 16 if you want to test CLA 16-bit*/

// declare your signals as reg or wire
reg [N-1:0] a;
reg [N-1:0] b;
reg cin;
wire [N-1:0] S;
wire cout;
wire Pout;
wire Gout;
integer i, j;

initial begin

// write the stimuli conditions

    $monitor("%d, %d, %d", a, b, S);
    a = 0; b=0; cin = 0;
    for (i = 0; i < 256; i=i+7) begin
        for (j = 0; j < 256; j=j+8) begin
            a = i; b = j; #1;
        end
    end
end



CLA_32bit dut (.a(a), .b(b), .cin(cin), .sum(S), .cout(cout), .Pout(Pout), .Gout(Gout));
// CLA_4bit dut1 (.a(a[3:0]), .b(b[3:0]), .cin(cin), .sum(S[3:0]), .cout(cout));
// CLA_16bit dut2 (.a(a[15:0]), .b(b[15:0]), .cin(cin), .sum(S[15:0]), .cout(cout), .Pout(Pout), .Gout(Gout));

initial begin
    $dumpfile("cla_32bit.vcd");
    $dumpvars(0, tb_cla_32bit);
end

endmodule

cla/cla_32bit.vcd
$date
	Tue Aug 20 12:00:59 2024
$end
$version
	Icarus Verilog
$end
$timescale
	1ps
$end
$scope module tb_cla_32bit $end
$var wire 1 ! cout $end
$var wire 32 " S [31:0] $end
$var wire 1 # Pout $end
$var wire 1 $ Gout $end
$var parameter 32 % N $end
$var reg 32 & a [31:0] $end
$var reg 32 ' b [31:0] $end
$var reg 1 ( cin $end
$var integer 32 ) i [31:0] $end
$var integer 32 * j [31:0] $end
$scope module dut $end
$var wire 32 + a [31:0] $end
$var wire 32 , b [31:0] $end
$var wire 1 ( cin $end
$var wire 1 ! cout $end
$var wire 32 - sum [31:0] $end
$var wire 1 # Pout $end
$var wire 1 . P1 $end
$var wire 1 / P0 $end
$var wire 1 $ Gout $end
$var wire 1 0 G1 $end
$var wire 1 1 G0 $end
$var wire 1 2 C32 $end
$var wire 1 3 C16 $end
$scope module cla5 $end
$var wire 16 4 a [15:0] $end
$var wire 16 5 b [15:0] $end
$var wire 1 ( cin $end
$var wire 1 6 cout $end
$var wire 16 7 sum [15:0] $end
$var wire 1 / Pout $end
$var wire 4 8 P [3:0] $end
$var wire 1 1 Gout $end
$var wire 4 9 G [3:0] $end
$var wire 1 : C8 $end
$var wire 1 ; C4 $end
$var wire 1 < C16 $end
$var wire 1 = C12 $end
$scope module cla0 $end
$var wire 1 > G $end
$var wire 1 ? P $end
$var wire 4 @ a [3:0] $end
$var wire 4 A b [3:0] $end
$var wire 1 ( cin $end
$var wire 4 B g [3:0] $end
$var wire 4 C p [3:0] $end
$var wire 4 D sum [3:0] $end
$var wire 4 E c [3:0] $end
$upscope $end
$scope module cla1 $end
$var wire 1 F G $end
$var wire 1 G P $end
$var wire 4 H a [3:0] $end
$var wire 4 I b [3:0] $end
$var wire 4 J g [3:0] $end
$var wire 4 K p [3:0] $end
$var wire 4 L sum [3:0] $end
$var wire 1 ; cin $end
$var wire 4 M c [3:0] $end
$upscope $end
$scope module cla2 $end
$var wire 1 N G $end
$var wire 1 O P $end
$var wire 4 P a [3:0] $end
$var wire 4 Q b [3:0] $end
$var wire 4 R g [3:0] $end
$var wire 4 S p [3:0] $end
$var wire 4 T sum [3:0] $end
$var wire 1 : cin $end
$var wire 4 U c [3:0] $end
$upscope $end
$scope module cla3 $end
$var wire 1 V G $end
$var wire 1 W P $end
$var wire 4 X a [3:0] $end
$var wire 4 Y b [3:0] $end
$var wire 4 Z g [3:0] $end
$var wire 4 [ p [3:0] $end
$var wire 4 \ sum [3:0] $end
$var wire 1 = cin $end
$var wire 4 ] c [3:0] $end
$upscope $end
$scope module lcu0 $end
$var wire 1 = C12 $end
$var wire 1 < C16 $end
$var wire 1 ; C4 $end
$var wire 1 : C8 $end
$var wire 1 ^ G0 $end
$var wire 1 _ G1 $end
$var wire 1 ` G2 $end
$var wire 1 a G3 $end
$var wire 1 1 GF $end
$var wire 1 b P0 $end
$var wire 1 c P1 $end
$var wire 1 d P2 $end
$var wire 1 e P3 $end
$var wire 1 / PF $end
$var wire 1 ( cin $end
$upscope $end
$upscope $end
$scope module cla6 $end
$var wire 16 f a [15:0] $end
$var wire 16 g b [15:0] $end
$var wire 1 h cout $end
$var wire 16 i sum [15:0] $end
$var wire 1 3 cin $end
$var wire 1 . Pout $end
$var wire 4 j P [3:0] $end
$var wire 1 0 Gout $end
$var wire 4 k G [3:0] $end
$var wire 1 l C8 $end
$var wire 1 m C4 $end
$var wire 1 n C16 $end
$var wire 1 o C12 $end
$scope module cla0 $end
$var wire 1 p G $end
$var wire 1 q P $end
$var wire 4 r a [3:0] $end
$var wire 4 s b [3:0] $end
$var wire 4 t g [3:0] $end
$var wire 4 u p [3:0] $end
$var wire 4 v sum [3:0] $end
$var wire 1 3 cin $end
$var wire 4 w c [3:0] $end
$upscope $end
$scope module cla1 $end
$var wire 1 x G $end
$var wire 1 y P $end
$var wire 4 z a [3:0] $end
$var wire 4 { b [3:0] $end
$var wire 4 | g [3:0] $end
$var wire 4 } p [3:0] $end
$var wire 4 ~ sum [3:0] $end
$var wire 1 m cin $end
$var wire 4 !" c [3:0] $end
$upscope $end
$scope module cla2 $end
$var wire 1 "" G $end
$var wire 1 #" P $end
$var wire 4 $" a [3:0] $end
$var wire 4 %" b [3:0] $end
$var wire 4 &" g [3:0] $end
$var wire 4 '" p [3:0] $end
$var wire 4 (" sum [3:0] $end
$var wire 1 l cin $end
$var wire 4 )" c [3:0] $end
$upscope $end
$scope module cla3 $end
$var wire 1 *" G $end
$var wire 1 +" P $end
$var wire 4 ," a [3:0] $end
$var wire 4 -" b [3:0] $end
$var wire 4 ." g [3:0] $end
$var wire 4 /" p [3:0] $end
$var wire 4 0" sum [3:0] $end
$var wire 1 o cin $end
$var wire 4 1" c [3:0] $end
$upscope $end
$scope module lcu0 $end
$var wire 1 o C12 $end
$var wire 1 n C16 $end
$var wire 1 m C4 $end
$var wire 1 l C8 $end
$var wire 1 2" G0 $end
$var wire 1 3" G1 $end
$var wire 1 4" G2 $end
$var wire 1 5" G3 $end
$var wire 1 0 GF $end
$var wire 1 6" P0 $end
$var wire 1 7" P1 $end
$var wire 1 8" P2 $end
$var wire 1 9" P3 $end
$var wire 1 . PF $end
$var wire 1 3 cin $end
$upscope $end
$upscope $end
$scope module lcu1 $end
$var wire 1 3 C16 $end
$var wire 1 2 C32 $end
$var wire 1 1 G0 $end
$var wire 1 0 G1 $end
$var wire 1 $ GF $end
$var wire 1 / P0 $end
$var wire 1 . P1 $end
$var wire 1 # PF $end
$var wire 1 ( cin $end
$upscope $end
$upscope $end
$upscope $end
$enddefinitions $end
$comment Show the parameter values. $end
$dumpall
b100000 %
$end
#0
$dumpvars
09"
08"
07"
06"
05"
04"
03"
02"
b0 1"
b0 0"
b0 /"
b0 ."
b0 -"
b0 ,"
0+"
0*"
b0 )"
b0 ("
b0 '"
b0 &"
b0 %"
b0 $"
0#"
0""
b0 !"
b0 ~
b0 }
b0 |
b0 {
b0 z
0y
0x
b0 w
b0 v
b0 u
b0 t
b0 s
b0 r
0q
0p
0o
0n
0m
0l
b0 k
b0 j
b0 i
0h
b0 g
b0 f
0e
0d
0c
0b
0a
0`
0_
0^
b0 ]
b0 \
b0 [
b0 Z
b0 Y
b0 X
0W
0V
b0 U
b0 T
b0 S
b0 R
b0 Q
b0 P
0O
0N
b0 M
b0 L
b0 K
b0 J
b0 I
b0 H
0G
0F
b0 E
b0 D
b0 C
b0 B
b0 A
b0 @
0?
0>
0=
0<
0;
0:
b0 9
b0 8
b0 7
06
b0 5
b0 4
03
02
01
00
0/
0.
b0 -
b0 ,
b0 +
b0 *
b0 )
0(
b0 '
b0 &
0$
0#
b0 "
0!
$end
#1000
b1000 "
b1000 -
b1000 7
b1000 D
b1000 C
b1000 A
b1000 5
b1000 '
b1000 ,
b1000 *
#2000
b0 D
b10000 "
b10000 -
b10000 7
b1 L
b0 C
b1 K
b0 A
b1 I
b10000 5
b10000 '
b10000 ,
b10000 *
#3000
b11000 "
b11000 -
b11000 7
b1000 D
b1000 C
b1000 A
b11000 5
b11000 '
b11000 ,
b11000 *
#4000
b0 D
b100000 "
b100000 -
b100000 7
b10 L
b0 C
b10 K
b0 A
b10 I
b100000 5
b100000 '
b100000 ,
b100000 *
#5000
b101000 "
b101000 -
b101000 7
b1000 D
b1000 C
b1000 A
b101000 5
b101000 '
b101000 ,
b101000 *
#6000
b0 D
b110000 "
b110000 -
b110000 7
b11 L
b0 C
b11 K
b0 A
b11 I
b110000 5
b110000 '
b110000 ,
b110000 *
#7000
b111000 "
b111000 -
b111000 7
b1000 D
b1000 C
b1000 A
b111000 5
b111000 '
b111000 ,
b111000 *
#8000
b0 D
b1000000 "
b1000000 -
b1000000 7
b100 L
b0 C
b100 K
b0 A
b100 I
b1000000 5
b1000000 '
b1000000 ,
b1000000 *
#9000
b1001000 "
b1001000 -
b1001000 7
b1000 D
b1000 C
b1000 A
b1001000 5
b1001000 '
b1001000 ,
b1001000 *
#10000
b0 D
b1010000 "
b1010000 -
b1010000 7
b101 L
b0 C
b101 K
b0 A
b101 I
b1010000 5
b1010000 '
b1010000 ,
b1010000 *
#11000
b1011000 "
b1011000 -
b1011000 7
b1000 D
b1000 C
b1000 A
b1011000 5
b1011000 '
b1011000 ,
b1011000 *
#12000
b0 D
b1100000 "
b1100000 -
b1100000 7
b110 L
b0 C
b110 K
b0 A
b110 I
b1100000 5
b1100000 '
b1100000 ,
b1100000 *
#13000
b1101000 "
b1101000 -
b1101000 7
b1000 D
b1000 C
b1000 A
b1101000 5
b1101000 '
b1101000 ,
b1101000 *
#14000
b0 D
b1110000 "
b1110000 -
b1110000 7
b111 L
b0 C
b111 K
b0 A
b111 I
b1110000 5
b1110000 '
b1110000 ,
b1110000 *
#15000
b1111000 "
b1111000 -
b1111000 7
b1000 D
b1000 C
b1000 A
b1111000 5
b1111000 '
b1111000 ,
b1111000 *
#16000
0c
b0 8
0G
b0 D
b10000000 "
b10000000 -
b10000000 7
b1000 L
b0 C
b1000 K
b0 A
b1000 I
b10000000 5
b10000000 '
b10000000 ,
b10000000 *
#17000
b10001000 "
b10001000 -
b10001000 7
b1000 D
b1000 C
b1000 A
b10001000 5
b10001000 '
b10001000 ,
b10001000 *
#18000
b0 D
b10010000 "
b10010000 -
b10010000 7
b1001 L
b0 C
b1001 K
b0 A
b1001 I
b10010000 5
b10010000 '
b10010000 ,
b10010000 *
#19000
b10011000 "
b10011000 -
b10011000 7
b1000 D
b1000 C
b1000 A
b10011000 5
b10011000 '
b10011000 ,
b10011000 *
#20000
b0 D
b10100000 "
b10100000 -
b10100000 7
b1010 L
b0 C
b1010 K
b0 A
b1010 I
b10100000 5
b10100000 '
b10100000 ,
b10100000 *
#21000
b10101000 "
b10101000 -
b10101000 7
b1000 D
b1000 C
b1000 A
b10101000 5
b10101000 '
b10101000 ,
b10101000 *
#22000
b0 D
b10110000 "
b10110000 -
b10110000 7
b1011 L
b0 C
b1011 K
b0 A
b1011 I
b10110000 5
b10110000 '
b10110000 ,
b10110000 *
#23000
b10111000 "
b10111000 -
b10111000 7
b1000 D
b1000 C
b1000 A
b10111000 5
b10111000 '
b10111000 ,
b10111000 *
#24000
0c
b0 8
0G
b0 D
b11000000 "
b11000000 -
b11000000 7
b1100 L
b0 C
b1100 K
b0 A
b1100 I
b11000000 5
b11000000 '
b11000000 ,
b11000000 *
#25000
b11001000 "
b11001000 -
b11001000 7
b1000 D
b1000 C
b1000 A
b11001000 5
b11001000 '
b11001000 ,
b11001000 *
#26000
b0 D
b11010000 "
b11010000 -
b11010000 7
b1101 L
b0 C
b1101 K
b0 A
b1101 I
b11010000 5
b11010000 '
b11010000 ,
b11010000 *
#27000
b11011000 "
b11011000 -
b11011000 7
b1000 D
b1000 C
b1000 A
b11011000 5
b11011000 '
b11011000 ,
b11011000 *
#28000
b0 D
b11100000 "
b11100000 -
b11100000 7
b1110 L
b0 C
b1110 K
b0 A
b1110 I
b11100000 5
b11100000 '
b11100000 ,
b11100000 *
#29000
b11101000 "
b11101000 -
b11101000 7
b1000 D
b1000 C
b1000 A
b11101000 5
b11101000 '
b11101000 ,
b11101000 *
#30000
1c
b10 8
1G
b0 D
b11110000 "
b11110000 -
b11110000 7
b1111 L
b0 C
b1111 K
b0 A
b1111 I
b11110000 5
b11110000 '
b11110000 ,
b11110000 *
#31000
b11111000 "
b11111000 -
b11111000 7
b1000 D
b1000 C
b1000 A
b11111000 5
b11111000 '
b11111000 ,
b11111000 *
#32000
0c
b0 8
0G
b0 L
b111 "
b111 -
b111 7
b111 D
b0 K
b111 C
b0 A
b0 I
b111 @
b0 5
b111 4
b0 '
b0 ,
b111 &
b111 +
b111 )
b0 *
#33000
1b
b1 8
1?
b1111 "
b1111 -
b1111 7
b1111 D
b1111 C
b1000 A
b1000 5
b1000 '
b1000 ,
b1000 *
#34000
0b
b0 8
0?
b111 D
b10111 "
b10111 -
b10111 7
b1 L
b111 C
b1 K
b0 A
b1 I
b10000 5
b10000 '
b10000 ,
b10000 *
#35000
1b
b1 8
1?
b11111 "
b11111 -
b11111 7
b1111 D
b1111 C
b1000 A
b11000 5
b11000 '
b11000 ,
b11000 *
#36000
0b
b0 8
0?
b111 D
b100111 "
b100111 -
b100111 7
b10 L
b111 C
b10 K
b0 A
b10 I
b100000 5
b100000 '
b100000 ,
b100000 *
#37000
1b
b1 8
1?
b101111 "
b101111 -
b101111 7
b1111 D
b1111 C
b1000 A
b101000 5
b101000 '
b101000 ,
b101000 *
#38000
0b
b0 8
0?
b111 D
b110111 "
b110111 -
b110111 7
b11 L
b111 C
b11 K
b0 A
b11 I
b110000 5
b110000 '
b110000 ,
b110000 *
#39000
1b
b1 8
1?
b111111 "
b111111 -
b111111 7
b1111 D
b1111 C
b1000 A
b111000 5
b111000 '
b111000 ,
b111000 *
#40000
0b
b0 8
0?
b111 D
b1000111 "
b1000111 -
b1000111 7
b100 L
b111 C
b100 K
b0 A
b100 I
b1000000 5
b1000000 '
b1000000 ,
b1000000 *
#41000
1b
b1 8
1?
b1001111 "
b1001111 -
b1001111 7
b1111 D
b1111 C
b1000 A
b1001000 5
b1001000 '
b1001000 ,
b1001000 *
#42000
0b
b0 8
0?
b111 D
b1010111 "
b1010111 -
b1010111 7
b101 L
b111 C
b101 K
b0 A
b101 I
b1010000 5
b1010000 '
b1010000 ,
b1010000 *
#43000
1b
b1 8
1?
b1011111 "
b1011111 -
b1011111 7
b1111 D
b1111 C
b1000 A
b1011000 5
b1011000 '
b1011000 ,
b1011000 *
#44000
0b
b0 8
0?
b111 D
b1100111 "
b1100111 -
b1100111 7
b110 L
b111 C
b110 K
b0 A
b110 I
b1100000 5
b1100000 '
b1100000 ,
b1100000 *
#45000
1b
b1 8
1?
b1101111 "
b1101111 -
b1101111 7
b1111 D
b1111 C
b1000 A
b1101000 5
b1101000 '
b1101000 ,
b1101000 *
#46000
0b
b0 8
0?
b111 D
b1110111 "
b1110111 -
b1110111 7
b111 L
b111 C
b111 K
b0 A
b111 I
b1110000 5
b1110000 '
b1110000 ,
b1110000 *
#47000
1b
b1 8
1?
b1111111 "
b1111111 -
b1111111 7
b1111 D
b1111 C
b1000 A
b1111000 5
b1111000 '
b1111000 ,
b1111000 *
#48000
0b
0c
0?
b0 8
0G
b111 D
b10000111 "
b10000111 -
b10000111 7
b1000 L
b111 C
b1000 K
b0 A
b1000 I
b10000000 5
b10000000 '
b10000000 ,
b10000000 *
#49000
1b
b1 8
1?
b10001111 "
b10001111 -
b10001111 7
b1111 D
b1111 C
b1000 A
b10001000 5
b10001000 '
b10001000 ,
b10001000 *
#50000
0b
b0 8
0?
b111 D
b10010111 "
b10010111 -
b10010111 7
b1001 L
b111 C
b1001 K
b0 A
b1001 I
b10010000 5
b10010000 '
b10010000 ,
b10010000 *
#51000
1b
b1 8
1?
b10011111 "
b10011111 -
b10011111 7
b1111 D
b1111 C
b1000 A
b10011000 5
b10011000 '
b10011000 ,
b10011000 *
#52000
0b
b0 8
0?
b111 D
b10100111 "
b10100111 -
b10100111 7
b1010 L
b111 C
b1010 K
b0 A
b1010 I
b10100000 5
b10100000 '
b10100000 ,
b10100000 *
#53000
1b
b1 8
1?
b10101111 "
b10101111 -
b10101111 7
b1111 D
b1111 C
b1000 A
b10101000 5
b10101000 '
b10101000 ,
b10101000 *
#54000
0b
b0 8
0?
b111 D
b10110111 "
b10110111 -
b10110111 7
b1011 L
b111 C
b1011 K
b0 A
b1011 I
b10110000 5
b10110000 '
b10110000 ,
b10110000 *
#55000
1b
b1 8
1?
b10111111 "
b10111111 -
b10111111 7
b1111 D
b1111 C
b1000 A
b10111000 5
b10111000 '
b10111000 ,
b10111000 *
#56000
0c
0b
0G
b0 8
0?
b111 D
b11000111 "
b11000111 -
b11000111 7
b1100 L
b111 C
b1100 K
b0 A
b1100 I
b11000000 5
b11000000 '
b11000000 ,
b11000000 *
#57000
1b
b1 8
1?
b11001111 "
b11001111 -
b11001111 7
b1111 D
b1111 C
b1000 A
b11001000 5
b11001000 '
b11001000 ,
b11001000 *
#58000
0b
b0 8
0?
b111 D
b11010111 "
b11010111 -
b11010111 7
b1101 L
b111 C
b1101 K
b0 A
b1101 I
b11010000 5
b11010000 '
b11010000 ,
b11010000 *
#59000
1b
b1 8
1?
b11011111 "
b11011111 -
b11011111 7
b1111 D
b1111 C
b1000 A
b11011000 5
b11011000 '
b11011000 ,
b11011000 *
#60000
0b
b0 8
0?
b111 D
b11100111 "
b11100111 -
b11100111 7
b1110 L
b111 C
b1110 K
b0 A
b1110 I
b11100000 5
b11100000 '
b11100000 ,
b11100000 *
#61000
1b
b1 8
1?
b11101111 "
b11101111 -
b11101111 7
b1111 D
b1111 C
b1000 A
b11101000 5
b11101000 '
b11101000 ,
b11101000 *
#62000
1c
1G
0b
b10 8
0?
b111 D
b11110111 "
b11110111 -
b11110111 7
b1111 L
b111 C
b1111 K
b0 A
b1111 I
b11110000 5
b11110000 '
b11110000 ,
b11110000 *
#63000
1b
b11 8
1?
b11111111 "
b11111111 -
b11111111 7
b1111 D
b1111 C
b1000 A
b11111000 5
b11111000 '
b11111000 ,
b11111000 *
#64000
0b
0?
0c
b0 8
0G
b0 L
b1110 "
b1110 -
b1110 7
b1110 D
b0 K
b1110 C
b0 A
b0 I
b1110 @
b0 5
b1110 4
b0 '
b0 ,
b1110 &
b1110 +
b1110 )
b0 *
#65000
b1 L
b1 M
1;
1^
b1 9
1>
b10110 "
b10110 -
b10110 7
b110 D
b1000 B
b110 C
b1000 A
b1000 5
b1000 '
b1000 ,
b1000 *
#66000
0;
0^
b0 9
0>
b0 M
b1110 D
b11110 "
b11110 -
b11110 7
b1 L
b0 B
b1110 C
b1 K
b0 A
b1 I
b10000 5
b10000 '
b10000 ,
b10000 *
#67000
b10 L
b11 M
1;
1^
b1 9
1>
b100110 "
b100110 -
b100110 7
b110 D
b1000 B
b110 C
b1000 A
b11000 5
b11000 '
b11000 ,
b11000 *
#68000
0;
0^
b0 9
0>
b0 M
b1110 D
b101110 "
b101110 -
b101110 7
b10 L
b0 B
b1110 C
b10 K
b0 A
b10 I
b100000 5
b100000 '
b100000 ,
b100000 *
#69000
b11 L
b1 M
1;
1^
b1 9
1>
b110110 "
b110110 -
b110110 7
b110 D
b1000 B
b110 C
b1000 A
b101000 5
b101000 '
b101000 ,
b101000 *
#70000
0;
0^
b0 9
0>
b0 M
b1110 D
b111110 "
b111110 -
b111110 7
b11 L
b0 B
b1110 C
b11 K
b0 A
b11 I
b110000 5
b110000 '
b110000 ,
b110000 *
#71000
b100 L
b111 M
1;
1^
b1 9
1>
b1000110 "
b1000110 -
b1000110 7
b110 D
b1000 B
b110 C
b1000 A
b111000 5
b111000 '
b111000 ,
b111000 *
#72000
0;
0^
b0 9
0>
b0 M
b1110 D
b1001110 "
b1001110 -
b1001110 7
b100 L
b0 B
b1110 C
b100 K
b0 A
b100 I
b1000000 5
b1000000 '
b1000000 ,
b1000000 *
#73000
b101 L
b1 M
1;
1^
b1 9
1>
b1010110 "
b1010110 -
b1010110 7
b110 D
b1000 B
b110 C
b1000 A
b1001000 5
b1001000 '
b1001000 ,
b1001000 *
#74000
0;
0^
b0 9
0>
b0 M
b1110 D
b1011110 "
b1011110 -
b1011110 7
b101 L
b0 B
b1110 C
b101 K
b0 A
b101 I
b1010000 5
b1010000 '
b1010000 ,
b1010000 *
#75000
b110 L
b11 M
1;
1^
b1 9
1>
b1100110 "
b1100110 -
b1100110 7
b110 D
b1000 B
b110 C
b1000 A
b1011000 5
b1011000 '
b1011000 ,
b1011000 *
#76000
0;
0^
b0 9
0>
b0 M
b1110 D
b1101110 "
b1101110 -
b1101110 7
b110 L
b0 B
b1110 C
b110 K
b0 A
b110 I
b1100000 5
b1100000 '
b1100000 ,
b1100000 *
#77000
b111 L
b1 M
1;
1^
b1 9
1>
b1110110 "
b1110110 -
b1110110 7
b110 D
b1000 B
b110 C
b1000 A
b1101000 5
b1101000 '
b1101000 ,
b1101000 *
#78000
0;
0^
b0 9
0>
b0 M
b1110 D
b1111110 "
b1111110 -
b1111110 7
b111 L
b0 B
b1110 C
b111 K
b0 A
b111 I
b1110000 5
b1110000 '
b1110000 ,
b1110000 *
#79000
b1000 L
b1111 M
1;
1^
b1 9
1>
b10000110 "
b10000110 -
b10000110 7
b110 D
b1000 B
b110 C
b1000 A
b1111000 5
b1111000 '
b1111000 ,
b1111000 *
#80000
0;
b0 T
0^
b0 U
0:
b0 9
0>
b0 M
0c
b0 8
0G
b1110 D
b10001110 "
b10001110 -
b10001110 7
b1000 L
b0 B
b1110 C
b1000 K
b0 A
b1000 I
b10000000 5
b10000000 '
b10000000 ,
b10000000 *
#81000
b1001 L
b1 M
1;
1^
b1 9
1>
b10010110 "
b10010110 -
b10010110 7
b110 D
b1000 B
b110 C
b1000 A
b10001000 5
b10001000 '
b10001000 ,
b10001000 *
#82000
0;
0^
b0 9
0>
b0 M
b1110 D
b10011110 "
b10011110 -
b10011110 7
b1001 L
b0 B
b1110 C
b1001 K
b0 A
b1001 I
b10010000 5
b10010000 '
b10010000 ,
b10010000 *
#83000
b1010 L
b11 M
1;
1^
b1 9
1>
b10100110 "
b10100110 -
b10100110 7
b110 D
b1000 B
b110 C
b1000 A
b10011000 5
b10011000 '
b10011000 ,
b10011000 *
#84000
0;
0^
b0 9
0>
b0 M
b1110 D
b10101110 "
b10101110 -
b10101110 7
b1010 L
b0 B
b1110 C
b1010 K
b0 A
b1010 I
b10100000 5
b10100000 '
b10100000 ,
b10100000 *
#85000
b1011 L
b1 M
1;
1^
b1 9
1>
b10110110 "
b10110110 -
b10110110 7
b110 D
b1000 B
b110 C
b1000 A
b10101000 5
b10101000 '
b10101000 ,
b10101000 *
#86000
0;
0^
b0 9
0>
b0 M
b1110 D
b10111110 "
b10111110 -
b10111110 7
b1011 L
b0 B
b1110 C
b1011 K
b0 A
b1011 I
b10110000 5
b10110000 '
b10110000 ,
b10110000 *
#87000
b1100 L
b111 M
1;
1^
b1 9
1>
b11000110 "
b11000110 -
b11000110 7
b110 D
b1000 B
b110 C
b1000 A
b10111000 5
b10111000 '
b10111000 ,
b10111000 *
#88000
b0 T
0;
b0 U
0:
0^
b0 9
0>
0c
b0 M
b0 8
0G
b1110 D
b11001110 "
b11001110 -
b11001110 7
b1100 L
b0 B
b1110 C
b1100 K
b0 A
b1100 I
b11000000 5
b11000000 '
b11000000 ,
b11000000 *
#89000
b1101 L
b1 M
1;
1^
b1 9
1>
b11010110 "
b11010110 -
b11010110 7
b110 D
b1000 B
b110 C
b1000 A
b11001000 5
b11001000 '
b11001000 ,
b11001000 *
#90000
0;
0^
b0 9
0>
b0 M
b1110 D
b11011110 "
b11011110 -
b11011110 7
b1101 L
b0 B
b1110 C
b1101 K
b0 A
b1101 I
b11010000 5
b11010000 '
b11010000 ,
b11010000 *
#91000
b1110 L
b11 M
1;
1^
b1 9
1>
b11100110 "
b11100110 -
b11100110 7
b110 D
b1000 B
b110 C
b1000 A
b11011000 5
b11011000 '
b11011000 ,
b11011000 *
#92000
0;
0^
b0 9
0>
b0 M
b1110 D
b11101110 "
b11101110 -
b11101110 7
b1110 L
b0 B
b1110 C
b1110 K
b0 A
b1110 I
b11100000 5
b11100000 '
b11100000 ,
b11100000 *
#93000
b1111 L
b1 M
1;
1^
b1 9
1>
b11110110 "
b11110110 -
b11110110 7
b110 D
b1000 B
b110 C
b1000 A
b11101000 5
b11101000 '
b11101000 ,
b11101000 *
#94000
b0 T
b0 U
0:
0;
0^
1c
b0 9
0>
b10 8
1G
b0 M
b1110 D
b11111110 "
b11111110 -
b11111110 7
b1111 L
b0 B
b1110 C
b1111 K
b0 A
b1111 I
b11110000 5
b11110000 '
b11110000 ,
b11110000 *
#95000
b1 T
b1 U
1:
b0 L
b1111 M
1;
1^
b1 9
1>
b100000110 "
b100000110 -
b100000110 7
b110 D
b1000 B
b110 C
b1000 A
b11111000 5
b11111000 '
b11111000 ,
b11111000 *
#96000
0;
b0 T
0^
b0 U
0:
b0 9
0>
b0 M
0c
b0 8
0G
b101 D
b10101 "
b10101 -
b10101 7
b1 L
b0 B
b101 C
b1 K
b0 A
b0 I
b101 @
b1 H
b0 5
b10101 4
b0 '
b0 ,
b10101 &
b10101 +
b10101 )
b0 *
#97000
b11101 "
b11101 -
b11101 7
b1101 D
b1101 C
b1000 A
b1000 5
b1000 '
b1000 ,
b1000 *
#98000
b10 M
b101 D
b100101 "
b100101 -
b100101 7
b10 L
b101 C
b1 J
b0 K
b0 A
b1 I
b10000 5
b10000 '
b10000 ,
b10000 *
#99000
b101101 "
b101101 -
b101101 7
b1101 D
b1101 C
b1000 A
b11000 5
b11000 '
b11000 ,
b11000 *
#100000
b0 M
b101 D
b110101 "
b110101 -
b110101 7
b11 L
b101 C
b0 J
b11 K
b0 A
b10 I
b100000 5
b100000 '
b100000 ,
b100000 *
